sfeprapy/__init__.py
sfeprapy/cli/__init__.py
sfeprapy/cli/__main__.py
sfeprapy/dat/__init__.py
sfeprapy/dat/steel_section.py
sfeprapy/func/__init__.py
sfeprapy/func/asciiplot.py
sfeprapy/func/cibse_guide_e.py
sfeprapy/func/fire_astm_e119.py
sfeprapy/func/fire_external_ec.py
sfeprapy/func/fire_hydrocarbon_ec.py
sfeprapy/func/fire_iso834.py
sfeprapy/func/fire_parametric_ec.py
sfeprapy/func/fire_parametric_ec_din.py
sfeprapy/func/heat_transfer_1d_finite_difference.py
sfeprapy/func/heat_transfer_1d_finite_difference_3.py
sfeprapy/func/heat_transfer_protected_steel_bs13381.py
sfeprapy/func/heat_transfer_protected_steel_ec.py
sfeprapy/func/heat_transfer_unprotected_steel_ec.py
sfeprapy/func/mcs.py
sfeprapy/func/mcs_gen.py
sfeprapy/func/mcs_obj.py
sfeprapy/func/pd_6688_1_2_2007.py
sfeprapy/func/pp.py
sfeprapy/func/stats_dist_fit.py
sfeprapy/mcs0/__init__.py
sfeprapy/mcs0/__main__.py
sfeprapy/mcs0/mcs0_calc.py
sfeprapy/mcs1/__init__.py
sfeprapy/mcs1/__main__.py
sfeprapy/mcs1/mcs1.py
sfeprapy/mcs1/mcs1_func_gen.py
sfeprapy/mcs1/mcs1_func_ky_req.py
sfeprapy/mcs1/mcs1_func_main.py
sfeprapy/mcs1/mcs1_obj.py
sfeprapy/mcs2/__init__.py
sfeprapy/mcs2/__main__.py
sfeprapy/mcs2/mcs2_calc.py
sfeprapy-0.8.1.dist-info/LICENSE
sfeprapy-0.8.1.dist-info/METADATA
sfeprapy-0.8.1.dist-info/WHEEL
sfeprapy-0.8.1.dist-info/entry_points.txt
sfeprapy-0.8.1.dist-info/top_level.txt
sfeprapy-0.8.1.dist-info/RECORD
