Metadata-Version: 2.1
Name: sfeprapy
Version: 0.8.1
Summary: Structural Fire Engineering - Probabilistic Reliability Assessment (Equivalent Time Exposure)
Home-page: https://github.com/fsepy/sfeprapy
Author: Ian Fu
Author-email: fuyans@gmail.com
License: UNKNOWN
Download-URL: https://github.com/fsepy/sfeprapy/archive/master.zip
Keywords: fire safety,structural fire engineering
Platform: UNKNOWN
Classifier: Programming Language :: Python :: 3
Classifier: Development Status :: 4 - Beta
Classifier: Environment :: Other Environment
Classifier: Intended Audience :: Developers
Classifier: License :: OSI Approved :: MIT License
Classifier: Operating System :: OS Independent
Classifier: Topic :: Scientific/Engineering
Requires-Dist: numpy (>=1.17.1)
Requires-Dist: pandas (>=1.1.1)
Requires-Dist: scipy (>=1.5.2)
Requires-Dist: matplotlib (>=3.2.2)
Requires-Dist: tqdm (>=4.50.2)
Requires-Dist: xlrd (>=1.2.0)
Requires-Dist: docopt (>=0.6)
Requires-Dist: openpyxl (>=3.0.3)
